<?xml version="1.0" encoding="UTF-8"?>
<tour appversion="6.1.8" apprev="17956" start="node114">
  <panorama id="node114" hideabout="1">
    <input leveltilesize="510" overlap="1" width="3500" height="3500" leveltileurl="tiles/node114/cf_%c/l_%l/c_%x/tile_%y.jpg" levelingroll="0" levelingpitch="0" levelbias="0.400" levelbiashidpi="1.000">
      <level width="3500" height="3500" predecode="0" preload="0"/>
      <level width="1750" height="1750" predecode="0" preload="0"/>
      <level width="875" height="875" predecode="0" preload="0"/>
      <level width="437" height="437" predecode="1" preload="1"/>
      <preview color="0x808080" strip="1"/>
    </input>
    <view fovmode="0" pannorth="0">
      <start fov="70" tilt="0" pan="45" projection="4"/>
      <flyin fov="170" tilt="-90" pan="0" projection="9"/>
      <min fovpixel="2" tilt="-90" pan="0"/>
      <max fovstereographic="270" fov="120" tilt="90" pan="360" fovfisheye="360" scaletofit="1"/>
    </view>
    <userdata heading="0" customnodeid="" latitude="" longitude="" info="" tags="SHP_13.3_var1" author="" source="" title="" datetime="" nodeid="node114" description="" copyright="" comment="">
      <mapcoords mapid="FloorPlan01" y="-1.58752" y_floorplan_percent="66.0571" x_floorplan_percent="60.5714" x="1.45569"/>
    </userdata>
    <hotspots width="180" height="20" wordwrap="1">
      <label backgroundalpha="1" borderalpha="1" background="1" textalpha="1" width="180" height="20" bordercolor="0x000000" border="1" backgroundcolor="0xffffff" borderradius="1" enabled="0" textcolor="0x000000" wordwrap="1"/>
      <polystyle mode="2" backgroundalpha="0.25098" borderalpha="1" bordercolor="0x595959" handcursor="1" backgroundcolor="0xffffff"/>
      <hotspot id="Point01" tilt="2.55" skinid="ht_node" pan="-272.35" target="" url="{node115}" title="" description=""/>
      <hotspot id="Point02" tilt="1.41" skinid="ht_node" pan="-359.42" target="" url="{node116}" title="" description=""/>
      <hotspot id="Point03" tilt="14.74" skinid="ht_node" pan="-18.93" target="" url="{node120}" title="" description=""/>
    </hotspots>
    <media/>
    <transition zoomin="0" zoomfov="20" zoomoutpause="1" softedge="0" blendtime="1" type="crossdissolve" blendcolor="0x000000" enabled="1" zoomout="0" zoomspeed="2"/>
    <animation syncanimationwithvideo="0" useinautorotation="0" animsequence="Animation01"/>
    <control contextfullscreen="1" dblclickfullscreen="0" lockedkeyboardzoom="0" lockedwheel="0" speedwheel="1" sensitivity="8" rubberband="0" lockedmouse="0" invertwheel="0" invertcontrol="1" hideabout="1" lockedkeyboard="0" contextprojections="1" simulatemass="1"/>
  </panorama>
  <panorama id="node115" hideabout="1">
    <input leveltilesize="510" overlap="1" width="3500" height="3500" leveltileurl="tiles/node115/cf_%c/l_%l/c_%x/tile_%y.jpg" levelingroll="0" levelingpitch="0" levelbias="0.400" levelbiashidpi="1.000">
      <level width="3500" height="3500" predecode="0" preload="0"/>
      <level width="1750" height="1750" predecode="0" preload="0"/>
      <level width="875" height="875" predecode="0" preload="0"/>
      <level width="437" height="437" predecode="1" preload="1"/>
      <preview color="0x808080" strip="1"/>
    </input>
    <view fovmode="0" pannorth="0">
      <start fov="70" tilt="0" pan="-45" projection="4"/>
      <flyin fov="170" tilt="-90" pan="0" projection="9"/>
      <min fovpixel="2" tilt="-90" pan="0"/>
      <max fovstereographic="270" fov="120" tilt="90" pan="360" fovfisheye="360" scaletofit="1"/>
    </view>
    <userdata heading="0" customnodeid="" latitude="" longitude="" info="" tags="SHP_13.3_var1" author="" source="" title="" datetime="" nodeid="node115" description="" copyright="" comment="">
      <mapcoords mapid="FloorPlan01" y="-1.58546" y_floorplan_percent="65.9714" x_floorplan_percent="50.0286" x="1.20232"/>
    </userdata>
    <hotspots width="180" height="20" wordwrap="1">
      <label backgroundalpha="1" borderalpha="1" background="1" textalpha="1" width="180" height="20" bordercolor="0x000000" border="1" backgroundcolor="0xffffff" borderradius="1" enabled="0" textcolor="0x000000" wordwrap="1"/>
      <polystyle mode="2" backgroundalpha="0.25098" borderalpha="1" bordercolor="0x595959" handcursor="1" backgroundcolor="0xffffff"/>
      <hotspot id="Point01" tilt="2.65" skinid="ht_node" pan="-87.06" target="" url="{node114}" title="" description=""/>
    </hotspots>
    <media/>
    <transition zoomin="0" zoomfov="20" zoomoutpause="1" softedge="0" blendtime="1" type="crossdissolve" blendcolor="0x000000" enabled="1" zoomout="0" zoomspeed="2"/>
    <animation syncanimationwithvideo="0" useinautorotation="0" animsequence="Animation01"/>
    <control contextfullscreen="1" dblclickfullscreen="0" lockedkeyboardzoom="0" lockedwheel="0" speedwheel="1" sensitivity="8" rubberband="0" lockedmouse="0" invertwheel="0" invertcontrol="1" hideabout="1" lockedkeyboard="0" contextprojections="1" simulatemass="1"/>
  </panorama>
  <panorama id="node116" hideabout="1">
    <input leveltilesize="510" overlap="1" width="3500" height="3500" leveltileurl="tiles/node116/cf_%c/l_%l/c_%x/tile_%y.jpg" levelingroll="0" levelingpitch="0" levelbias="0.400" levelbiashidpi="1.000">
      <level width="3500" height="3500" predecode="0" preload="0"/>
      <level width="1750" height="1750" predecode="0" preload="0"/>
      <level width="875" height="875" predecode="0" preload="0"/>
      <level width="437" height="437" predecode="1" preload="1"/>
      <preview color="0x808080" strip="1"/>
    </input>
    <view fovmode="0" pannorth="0">
      <start fov="70" tilt="0" pan="-90" projection="4"/>
      <flyin fov="170" tilt="-90" pan="0" projection="9"/>
      <min fovpixel="2" tilt="-90" pan="0"/>
      <max fovstereographic="270" fov="120" tilt="90" pan="360" fovfisheye="360" scaletofit="1"/>
    </view>
    <userdata heading="0" customnodeid="" latitude="" longitude="" info="" tags="SHP_13.3_var1" author="" source="" title="" datetime="" nodeid="node116" description="" copyright="" comment="">
      <mapcoords mapid="FloorPlan01" y="-1.37466" y_floorplan_percent="57.2" x_floorplan_percent="60.3143" x="1.44951"/>
    </userdata>
    <hotspots width="180" height="20" wordwrap="1">
      <label backgroundalpha="1" borderalpha="1" background="1" textalpha="1" width="180" height="20" bordercolor="0x000000" border="1" backgroundcolor="0xffffff" borderradius="1" enabled="0" textcolor="0x000000" wordwrap="1"/>
      <polystyle mode="2" backgroundalpha="0.25098" borderalpha="1" bordercolor="0x595959" handcursor="1" backgroundcolor="0xffffff"/>
      <hotspot id="Point01" tilt="1.13" skinid="ht_node" pan="-91.27" target="" url="{node117}" title="" description=""/>
      <hotspot id="Point02" tilt="1.93" skinid="ht_node" pan="-271.81" target="" url="{node114}" title="" description=""/>
      <hotspot id="Point03" tilt="31.73" skinid="ht_node" pan="-146.14" target="" url="{node120}" title="" description=""/>
    </hotspots>
    <media/>
    <transition zoomin="0" zoomfov="20" zoomoutpause="1" softedge="0" blendtime="1" type="crossdissolve" blendcolor="0x000000" enabled="1" zoomout="0" zoomspeed="2"/>
    <animation syncanimationwithvideo="0" useinautorotation="0" animsequence="Animation01"/>
    <control contextfullscreen="1" dblclickfullscreen="0" lockedkeyboardzoom="0" lockedwheel="0" speedwheel="1" sensitivity="8" rubberband="0" lockedmouse="0" invertwheel="0" invertcontrol="1" hideabout="1" lockedkeyboard="0" contextprojections="1" simulatemass="1"/>
  </panorama>
  <panorama id="node117" hideabout="1">
    <input leveltilesize="510" overlap="1" width="3500" height="3500" leveltileurl="tiles/node117/cf_%c/l_%l/c_%x/tile_%y.jpg" levelingroll="0" levelingpitch="0" levelbias="0.400" levelbiashidpi="1.000">
      <level width="3500" height="3500" predecode="0" preload="0"/>
      <level width="1750" height="1750" predecode="0" preload="0"/>
      <level width="875" height="875" predecode="0" preload="0"/>
      <level width="437" height="437" predecode="1" preload="1"/>
      <preview color="0x808080" strip="1"/>
    </input>
    <view fovmode="0" pannorth="0">
      <start fov="70" tilt="0" pan="-90" projection="4"/>
      <flyin fov="170" tilt="-90" pan="0" projection="9"/>
      <min fovpixel="2" tilt="-90" pan="0"/>
      <max fovstereographic="270" fov="120" tilt="90" pan="360" fovfisheye="360" scaletofit="1"/>
    </view>
    <userdata heading="0" customnodeid="" latitude="" longitude="" info="" tags="SHP_13.3_var1" author="" source="" title="" datetime="" nodeid="node117" description="" copyright="" comment="">
      <mapcoords mapid="FloorPlan01" y="-1.1618" y_floorplan_percent="48.3429" x_floorplan_percent="60.4286" x="1.45226"/>
    </userdata>
    <hotspots width="180" height="20" wordwrap="1">
      <label backgroundalpha="1" borderalpha="1" background="1" textalpha="1" width="180" height="20" bordercolor="0x000000" border="1" backgroundcolor="0xffffff" borderradius="1" enabled="0" textcolor="0x000000" wordwrap="1"/>
      <polystyle mode="2" backgroundalpha="0.25098" borderalpha="1" bordercolor="0x595959" handcursor="1" backgroundcolor="0xffffff"/>
      <hotspot id="Point01" tilt="1.27" skinid="ht_node" pan="-90.71" target="" url="{node118}" title="" description=""/>
      <hotspot id="Point02" tilt="1.49" skinid="ht_node" pan="-270.94" target="" url="{node116}" title="" description=""/>
      <hotspot id="Point03" tilt="22.04" skinid="ht_node" pan="-236.4" target="" url="{node120}" title="" description=""/>
    </hotspots>
    <media/>
    <transition zoomin="0" zoomfov="20" zoomoutpause="1" softedge="0" blendtime="1" type="crossdissolve" blendcolor="0x000000" enabled="1" zoomout="0" zoomspeed="2"/>
    <animation syncanimationwithvideo="0" useinautorotation="0" animsequence="Animation01"/>
    <control contextfullscreen="1" dblclickfullscreen="0" lockedkeyboardzoom="0" lockedwheel="0" speedwheel="1" sensitivity="8" rubberband="0" lockedmouse="0" invertwheel="0" invertcontrol="1" hideabout="1" lockedkeyboard="0" contextprojections="1" simulatemass="1"/>
  </panorama>
  <panorama id="node118" hideabout="1">
    <input leveltilesize="510" overlap="1" width="3500" height="3500" leveltileurl="tiles/node118/cf_%c/l_%l/c_%x/tile_%y.jpg" levelingroll="0" levelingpitch="0" levelbias="0.400" levelbiashidpi="1.000">
      <level width="3500" height="3500" predecode="0" preload="0"/>
      <level width="1750" height="1750" predecode="0" preload="0"/>
      <level width="875" height="875" predecode="0" preload="0"/>
      <level width="437" height="437" predecode="1" preload="1"/>
      <preview color="0x808080" strip="1"/>
    </input>
    <view fovmode="0" pannorth="0">
      <start fov="70" tilt="0" pan="-90" projection="4"/>
      <flyin fov="170" tilt="-90" pan="0" projection="9"/>
      <min fovpixel="2" tilt="-90" pan="0"/>
      <max fovstereographic="270" fov="120" tilt="90" pan="360" fovfisheye="360" scaletofit="1"/>
    </view>
    <userdata heading="0" customnodeid="" latitude="" longitude="" info="" tags="SHP_13.3_var1" author="" source="" title="" datetime="" nodeid="node118" description="" copyright="" comment="">
      <mapcoords mapid="FloorPlan01" y="-0.990143" y_floorplan_percent="41.2" x_floorplan_percent="60.0857" x="1.44402"/>
    </userdata>
    <hotspots width="180" height="20" wordwrap="1">
      <label backgroundalpha="1" borderalpha="1" background="1" textalpha="1" width="180" height="20" bordercolor="0x000000" border="1" backgroundcolor="0xffffff" borderradius="1" enabled="0" textcolor="0x000000" wordwrap="1"/>
      <polystyle mode="2" backgroundalpha="0.25098" borderalpha="1" bordercolor="0x595959" handcursor="1" backgroundcolor="0xffffff"/>
      <hotspot id="Point01" tilt="1.13" skinid="ht_node" pan="-85.37" target="" url="{node119}" title="" description=""/>
      <hotspot id="Point02" tilt="1.22" skinid="ht_node" pan="-270.99" target="" url="{node117}" title="" description=""/>
      <hotspot id="Point03" tilt="17.73" skinid="ht_node" pan="-241.95" target="" url="{node120}" title="" description=""/>
    </hotspots>
    <media/>
    <transition zoomin="0" zoomfov="20" zoomoutpause="1" softedge="0" blendtime="1" type="crossdissolve" blendcolor="0x000000" enabled="1" zoomout="0" zoomspeed="2"/>
    <animation syncanimationwithvideo="0" useinautorotation="0" animsequence="Animation01"/>
    <control contextfullscreen="1" dblclickfullscreen="0" lockedkeyboardzoom="0" lockedwheel="0" speedwheel="1" sensitivity="8" rubberband="0" lockedmouse="0" invertwheel="0" invertcontrol="1" hideabout="1" lockedkeyboard="0" contextprojections="1" simulatemass="1"/>
  </panorama>
  <panorama id="node119" hideabout="1">
    <input leveltilesize="510" overlap="1" width="3500" height="3500" leveltileurl="tiles/node119/cf_%c/l_%l/c_%x/tile_%y.jpg" levelingroll="0" levelingpitch="0" levelbias="0.400" levelbiashidpi="1.000">
      <level width="3500" height="3500" predecode="0" preload="0"/>
      <level width="1750" height="1750" predecode="0" preload="0"/>
      <level width="875" height="875" predecode="0" preload="0"/>
      <level width="437" height="437" predecode="1" preload="1"/>
      <preview color="0x808080" strip="1"/>
    </input>
    <view fovmode="0" pannorth="0">
      <start fov="70" tilt="0" pan="45" projection="4"/>
      <flyin fov="170" tilt="-90" pan="0" projection="9"/>
      <min fovpixel="2" tilt="-90" pan="0"/>
      <max fovstereographic="270" fov="120" tilt="90" pan="360" fovfisheye="360" scaletofit="1"/>
    </view>
    <userdata heading="0" customnodeid="" latitude="" longitude="" info="" tags="SHP_13.3_var1" author="" source="" title="" datetime="" nodeid="node119" description="" copyright="" comment="">
      <mapcoords mapid="FloorPlan01" y="-0.787582" y_floorplan_percent="32.7714" x_floorplan_percent="60.3143" x="1.44951"/>
    </userdata>
    <hotspots width="180" height="20" wordwrap="1">
      <label backgroundalpha="1" borderalpha="1" background="1" textalpha="1" width="180" height="20" bordercolor="0x000000" border="1" backgroundcolor="0xffffff" borderradius="1" enabled="0" textcolor="0x000000" wordwrap="1"/>
      <polystyle mode="2" backgroundalpha="0.25098" borderalpha="1" bordercolor="0x595959" handcursor="1" backgroundcolor="0xffffff"/>
      <hotspot id="Point01" tilt="1.27" skinid="ht_node" pan="-270.57" target="" url="{node118}" title="" description=""/>
      <hotspot id="Point02" tilt="11.74" skinid="ht_node" pan="-259.24" target="" url="{node120}" title="" description=""/>
    </hotspots>
    <media/>
    <transition zoomin="0" zoomfov="20" zoomoutpause="1" softedge="0" blendtime="1" type="crossdissolve" blendcolor="0x000000" enabled="1" zoomout="0" zoomspeed="2"/>
    <animation syncanimationwithvideo="0" useinautorotation="0" animsequence="Animation01"/>
    <control contextfullscreen="1" dblclickfullscreen="0" lockedkeyboardzoom="0" lockedwheel="0" speedwheel="1" sensitivity="8" rubberband="0" lockedmouse="0" invertwheel="0" invertcontrol="1" hideabout="1" lockedkeyboard="0" contextprojections="1" simulatemass="1"/>
  </panorama>
  <panorama id="node120" hideabout="1">
    <input leveltilesize="510" overlap="1" width="3500" height="3500" leveltileurl="tiles/node120/cf_%c/l_%l/c_%x/tile_%y.jpg" levelingroll="0" levelingpitch="0" levelbias="0.400" levelbiashidpi="1.000">
      <level width="3500" height="3500" predecode="0" preload="0"/>
      <level width="1750" height="1750" predecode="0" preload="0"/>
      <level width="875" height="875" predecode="0" preload="0"/>
      <level width="437" height="437" predecode="1" preload="1"/>
      <preview color="0x808080" strip="1"/>
    </input>
    <view fovmode="0" pannorth="0">
      <start fov="70" tilt="0" pan="0" projection="4"/>
      <flyin fov="170" tilt="-90" pan="0" projection="9"/>
      <min fovpixel="2" tilt="-90" pan="0"/>
      <max fovstereographic="270" fov="120" tilt="90" pan="360" fovfisheye="360" scaletofit="1"/>
    </view>
    <userdata heading="0" customnodeid="" latitude="" longitude="" info="" tags="SHP_13.3_var1" author="" source="" title="" datetime="" nodeid="node120" description="" copyright="" comment="">
      <mapcoords mapid="FloorPlan01" y="-1.22154" y_floorplan_percent="50.8286" x_floorplan_percent="65.8286" x="1.58203"/>
    </userdata>
    <hotspots width="180" height="20" wordwrap="1">
      <label backgroundalpha="1" borderalpha="1" background="1" textalpha="1" width="180" height="20" bordercolor="0x000000" border="1" backgroundcolor="0xffffff" borderradius="1" enabled="0" textcolor="0x000000" wordwrap="1"/>
      <polystyle mode="2" backgroundalpha="0.25098" borderalpha="1" bordercolor="0x595959" handcursor="1" backgroundcolor="0xffffff"/>
      <hotspot id="Point01" tilt="-2.92" skinid="ht_node" pan="-276.97" target="" url="{node114}" title="" description=""/>
      <hotspot id="Point02" tilt="-1.78" skinid="ht_node" pan="-84.94" target="" url="{node119}" title="" description=""/>
      <hotspot id="Point03" tilt="-9.23" skinid="ht_node" pan="-74.11" target="" url="{node118}" title="" description=""/>
      <hotspot id="Point04" tilt="-15.66" skinid="ht_node" pan="-300.66" target="" url="{node116}" title="" description=""/>
      <hotspot id="Point05" tilt="-18.98" skinid="ht_node" pan="-55.09" target="" url="{node117}" title="" description=""/>
    </hotspots>
    <media/>
    <transition zoomin="0" zoomfov="20" zoomoutpause="1" softedge="0" blendtime="1" type="crossdissolve" blendcolor="0x000000" enabled="1" zoomout="0" zoomspeed="2"/>
    <animation syncanimationwithvideo="0" useinautorotation="0" animsequence="Animation01"/>
    <control contextfullscreen="1" dblclickfullscreen="0" lockedkeyboardzoom="0" lockedwheel="0" speedwheel="1" sensitivity="8" rubberband="0" lockedmouse="0" invertwheel="0" invertcontrol="1" hideabout="1" lockedkeyboard="0" contextprojections="1" simulatemass="1"/>
  </panorama>
  <masternode>
    <userdata heading="0" customnodeid="" latitude="" longitude="" info="" tags="" author="" source="" title="" datetime="" nodeid="master" description="" copyright="" comment=""/>
  </masternode>
  <map id="FloorPlan01" transparent="1" width="3500" height="3500" floorplannorth="359.66" bgcolor="rgba(255, 255, 255, 0)" type="file" tileformat="png" title="" zoomlevels="5"/>
</tour>
